flask_mongo_model-0.0.2.dist-info/DESCRIPTION.rst
flask_mongo_model-0.0.2.dist-info/METADATA
flask_mongo_model-0.0.2.dist-info/RECORD
flask_mongo_model-0.0.2.dist-info/WHEEL
flask_mongo_model-0.0.2.dist-info/metadata.json
flask_mongo_model-0.0.2.dist-info/top_level.txt
mongo_model/__init__.py
mongo_model/mongo_model.py
mongo_model/mongo_model_test.py
