Metadata-Version: 2.0
Name: flask-mongo-model
Version: 0.0.2
Summary: A module provides basic ORM feature for MongoDB to Flask applications.
Home-page: UNKNOWN
Author: Ares Ou
Author-email: aresowj@gmail.com
License: MIT
Platform: UNKNOWN
